mcp_weather_sse/__init__.py
mcp_weather_sse/__main__.py
mcp_weather_sse/server.py
mcp_weather_sse_release-0.1.0.dist-info/METADATA
mcp_weather_sse_release-0.1.0.dist-info/WHEEL
mcp_weather_sse_release-0.1.0.dist-info/entry_points.txt
mcp_weather_sse_release-0.1.0.dist-info/top_level.txt
mcp_weather_sse_release-0.1.0.dist-info/RECORD
